cache_performance_model/__init__.py
cache_performance_model/cache_model.py
cache_performance_model/types.py
cache_performance_model/version.py
cache_performance_model-0.1.6.dist-info/METADATA
cache_performance_model-0.1.6.dist-info/WHEEL
cache_performance_model-0.1.6.dist-info/top_level.txt
cache_performance_model-0.1.6.dist-info/RECORD
