Metadata-Version: 2.2
Name: cache_performance_model
Version: 0.1.6
Summary: Cache performance model
Home-page: https://github.com/aignacio/cache_performance_model
Author: aignacio (Anderson Ignacio)
Author-email: <anderson@aignacio.com>
License: MIT
Project-URL: Bug Tracker, https://github.com/aignacio/cache_performance_model/issues
Project-URL: Source Code, https://github.com/aignacio/cache_performance_model
Keywords: modeling,cache,hdl,design
Classifier: Development Status :: 3 - Alpha
Classifier: Intended Audience :: Developers
Classifier: Programming Language :: Python :: 3
Classifier: License :: OSI Approved :: MIT License
Classifier: Operating System :: Unix
Classifier: Operating System :: MacOS :: MacOS X
Classifier: Operating System :: Microsoft :: Windows
Requires-Python: >=3.6
Requires-Dist: numpy
Provides-Extra: test
Requires-Dist: pytest; extra == "test"
Dynamic: author
Dynamic: author-email
Dynamic: classifier
Dynamic: description
Dynamic: description-content-type
Dynamic: home-page
Dynamic: keywords
Dynamic: license
Dynamic: project-url
Dynamic: provides-extra
Dynamic: requires-dist
Dynamic: requires-python
Dynamic: summary
